mcp_server_aact/__init__.py
mcp_server_aact/database.py
mcp_server_aact/errors.py
mcp_server_aact/handlers.py
mcp_server_aact/memo_manager.py
mcp_server_aact/prompt_config.py
mcp_server_aact/prompts.py
mcp_server_aact/resources.py
mcp_server_aact/server.py
mcp_server_aact/tools.py
mseep_mcp_server_aact-0.4.3.dist-info/licenses/LICENSE
mseep_mcp_server_aact-0.4.3.dist-info/METADATA
mseep_mcp_server_aact-0.4.3.dist-info/WHEEL
mseep_mcp_server_aact-0.4.3.dist-info/entry_points.txt
mseep_mcp_server_aact-0.4.3.dist-info/top_level.txt
mseep_mcp_server_aact-0.4.3.dist-info/RECORD
