Metadata-Version: 2.4
Name: mseep-mcp-server-aact
Version: 0.4.3
Summary: MCP server for AACT clinical trials database
Author-email: mseep <support@skydeck.ai>
Requires-Python: >=3.10
License-File: LICENSE
Requires-Dist: mcp
Requires-Dist: psycopg2-binary
Requires-Dist: python-dotenv
Provides-Extra: test
Requires-Dist: pytest; extra == "test"
Requires-Dist: pytest-asyncio; extra == "test"
Dynamic: license-file
